{
    "name": "Futuristt",
    "author": "Carlo Wisse",
    "maintainers": [
        "Carlo Wisse <contact@carlowisse.com>"
    ],
    "type": "dark",
    "semanticClass": "futuristt",
    "colors": {
        "focusBorder": "#000000",
        "foreground": "#FFFFFF",
        "widget.shadow": "#000000",
        "selection.background": "#999999",
        "descriptionForeground": "#FFFFFF",
        "errorForeground": "#eb0869",
        "scrollbar.shadow": "#000000",
        "editorLink.activeForeground": "#FFFFFF",
        "progressBar.background": "#32D698",
        "textLink.foreground": "#eb0869",
        "textLink.activeForeground": "#FFFFFF",
        "editorBracketMatch.background": "#0c0d0e",
        "editor.foreground": "#ffffff",
        "editor.findRangeHighlightBackground": "#252525",
        "editorOverviewRuler.border": "#0c0d0e",
        "editorHoverWidget.background": "#0c0d0e",
        "editorHoverWidget.border": "#000000",
        "editorIndentGuide.background": "#222222",
        "editorGroup.border": "#252525",
        "editorGutter.modifiedBackground": "#f887ff60",
        "editorGutter.addedBackground": "#32D69860",
        "editorGutter.deletedBackground": "#eb086960",
        "tab.activeBorder": "#eb0869",
        "tab.unfocusedActiveBorder": "#777777",
        "tab.inactiveBackground": "#0c0d0e",
        "tab.hoverBackground": "#252525",
        "tab.unfocusedActiveForeground": "#ffffff",
        "tab.unfocusedInactiveForeground": "#777777",
        "tab.border": "#0c0d0e",
        "statusBar.noFolderBackground": "#0a0a0a60",
        "statusBar.debuggingBackground": "#eb0869",
        "statusBar.debuggingForeground": "#ffffff",
        "activityBarBadge.background": "#eb0869",
        "activityBarBadge.foreground": "#ffffff",
        "sideBarSectionHeader.background": "#0c0d0e",
        "input.background": "#3a3a3a",
        "input.foreground": "#ffffff",
        "input.placeholderForeground": "#ffffff60",
        "input.border": "#eb086900",
        "inputOption.activeBorder": "#eb0869",
        "inputValidation.errorBorder": "#eb0869",
        "inputValidation.infoBorder": "#f887ff",
        "inputValidation.warningBorder": "#F3F359",
        "dropdown.background": "#0c0d0e",
        "dropdown.border": "#FFFFFF10",
        "list.hoverForeground": "#FFFFFF",
        "list.hoverBackground": "#252525",
        "list.activeSelectionBackground": "#3a3a3a",
        "list.activeSelectionForeground": "#eb0869",
        "list.inactiveSelectionForeground": "#eb0869",
        "list.inactiveSelectionBackground": "#0c0d0e",
        "list.focusBackground": "#ffffff44",
        "list.focusForeground": "#ffffff",
        "list.highlightForeground": "#eb0869",
        "list.warningForeground": "#F3F359",
        "list.errorForeground": "#eb0869",
        "scrollbarSlider.background": "#ffffff24",
        "scrollbarSlider.hoverBackground": "#eb086977",
        "scrollbarSlider.activeBackground": "#ffffff24",
        "editorSuggestWidget.background": "#0c0d0e",
        "editorSuggestWidget.foreground": "#ffffff",
        "editorSuggestWidget.highlightForeground": "#eb0869",
        "editorSuggestWidget.selectedBackground": "#3a3a3a",
        "editorSuggestWidget.border": "#222222",
        "editorError.foreground": "#eb0869",
        "editorWarning.foreground": "#F3F35970",
        "editorWidget.background": "#0c0d0e",
        "editorMarkerNavigation.background": "#ffffff05",
        "diffEditor.insertedTextBackground": "#32D69815",
        "diffEditor.removedTextBackground": "#eb086990",
        "badge.background": "#0a0a0a30",
        "badge.foreground": "#3a3a3a",
        "button.background": "#77777750",
        "extensionButton.prominentBackground": "#32D69890",
        "extensionButton.prominentHoverBackground": "#32D698",
        "peekView.border": "#0a0a0a30",
        "peekViewEditor.background": "#ffffff05",
        "peekViewTitle.background": "#ffffff05",
        "peekViewResult.background": "#ffffff05",
        "peekViewEditorGutter.background": "#ffffff05",
        "peekViewTitleDescription.foreground": "#ffffff60",
        "debugToolBar.background": "#0c0d0e",
        "pickerGroup.foreground": "#eb0869",
        "gitDecoration.deletedResourceForeground": "#eb0869",
        "gitDecoration.conflictingResourceForeground": "#F3F359",
        "gitDecoration.modifiedResourceForeground": "#616161",
        "gitDecoration.untrackedResourceForeground": "#32D698",
        "gitDecoration.ignoredResourceForeground": "#3a3a3a",
        "editorInfo.foreground": "#616161",
        "editor.hoverHighlightBackground": "#181818",
        "peekViewEditor.matchHighlightBackground": "#181818",
        "editor.wordHighlightBackground": "#181818",
        "editor.wordHighlightStrongBackground": "#181818",
        "editorGutter.commentRangeForeground": "#f887ff60",
        "editorIndentGuide.activeBackground": "#616161",
        "breadcrumb.foreground": "#f8f8f8c2",
        "activityBar.activeBorder": "#111111",
        "activityBar.background": "#111111",
        "activityBar.border": "#222222",
        "activityBar.foreground": "#cccccc",
        "activityBar.inactiveForeground": "#555555",
        "editor.background": "#000000",
        "editor.findMatchBackground": "#77dd77c0",
        "editor.findMatchHighlightBackground": "#FFFFFF50",
        "editor.lineHighlightBackground": "#111111",
        "editor.selectionBackground": "#555555",
        "editor.selectionHighlightBackground": "#444444",
        "editor.selectionHighlightBorder": "#000000",
        "editorGutter.background": "#000000",
        "editorCursor.background": "#000000",
        "editorCursor.foreground": "#eeeeee",
        "editorGroupHeader.tabsBackground": "#111111",
        "editorGroupHeader.tabsBorder": "#222222",
        "editorLineNumber.activeForeground": "#eeeeee",
        "editorLineNumber.foreground": "#555555",
        "editorWhitespace.foreground": "#555555",
        "menu.background": "#000000",
        "menu.border": "#333333",
        "menu.foreground": "#cccccc",
        "menu.selectionBackground": "#222222",
        "menu.selectionBorder": "#111111",
        "menu.selectionForeground": "#eeeeee",
        "menu.separatorBackground": "#333333",
        "menubar.selectionBackground": "#000000",
        "menubar.selectionBorder": "#000000",
        "menubar.selectionForeground": "#eeeeee",
        "minimap.background": "#111111",
        "minimap.errorHighlight": "#111111",
        "minimap.findMatchHighlight": "#111111",
        "minimap.foregroundOpacity": "#000000c0",
        "minimap.selectionHighlight": "#111111",
        "minimap.selectionOccurrenceHighlight": "#111111",
        "minimap.warningHighlight": "#111111",
        "minimapGutter.addedBackground": "#111111",
        "minimapGutter.deletedBackground": "#111111",
        "minimapGutter.modifiedBackground": "#111111",
        "minimapSlider.activeBackground": "#111111",
        "minimapSlider.background": "#111111",
        "minimapSlider.hoverBackground": "#111111",
        "panel.background": "#111111",
        "panel.border": "#222222",
        "panelTitle.activeBorder": "#111111",
        "panelTitle.activeForeground": "#eeeeee",
        "panelTitle.inactiveForeground": "#666666",
        "sideBar.background": "#000000",
        "sideBar.border": "#222222",
        "sideBar.foreground": "#999999",
        "sideBarTitle.foreground": "#999999",
        "statusBar.background": "#111111",
        "statusBar.border": "#333333",
        "statusBar.foreground": "#CCCCCC",
        "statusBarItem.remoteBackground": "#111111",
        "statusBarItem.remoteForeground": "#CCCCCC",
        "tab.activeBackground": "#333333c0",
        "tab.activeForeground": "#eeeeee",
        "tab.inactiveForeground": "#999999",
        "tab.unfocusedActiveBackground": "#222222c0",
        "terminal.background": "#000000",
        "terminal.border": "#333333",
        "terminal.foreground": "#2FA43D",
        "terminal.tab.activeBorder": "#2FA43D",
        "terminal.ansiBlack": "#2FA43D",
        "terminal.ansiBlue": "#2FA43D",
        "terminal.ansiBrightBlack": "#2FA43D",
        "terminal.ansiBrightBlue": "#1f75fe",
        "terminal.ansiBrightCyan": "#2FA43D",
        "terminal.ansiBrightGreen": "#2FA43D",
        "terminal.ansiBrightMagenta": "#2FA43D",
        "terminal.ansiBrightRed": "#ee204d",
        "terminal.ansiBrightWhite": "#2FA43D",
        "terminal.ansiBrightYellow": "#2FA43D",
        "terminal.ansiCyan": "#2FA43D",
        "terminal.ansiGreen": "#2FA43D",
        "terminal.ansiMagenta": "#2FA43D",
        "terminal.ansiRed": "#ee204d",
        "terminal.ansiWhite": "#2FA43D",
        "terminal.ansiYellow": "#FFD505",
        "terminalCursor.background": "#000000",
        "terminalCursor.foreground": "#2FA43D",
        "titleBar.activeBackground": "#111111",
        "titleBar.activeForeground": "#cccccc",
        "titleBar.border": "#222222",
        "titleBar.inactiveBackground": "#111111",
        "titleBar.inactiveForeground": "#cccccc"
    },
    "tokenColors": [
        {
            "name": "Comment",
            "scope": [
                "comment",
                "comment storage.type",
                "comment variable",
                "comment support.variable",
                "comment support.class",
                "comment support.type",
                "comment entity.name.type",
                "comment entity.name.class",
                "comment keyword.operator",
                "comment: comment",
                "comment.line.double-slash",
                "comment entity.name.class",
                "comment entity.name.type",
                "comment keyword.operator",
                "comment support.class",
                "comment support.type",
                "comment support.variable",
                "comment variable",
                "Double-Slashed Comment"
            ],
            "settings": {
                "foreground": "#888888"
            }
        },
        {
            "name": "String",
            "scope": "string",
            "settings": {
                "foreground": "#32D698"
            }
        },
        {
            "name": "String Quoted",
            "scope": "string.quoted",
            "settings": {
                "foreground": "#32D698"
            }
        },
        {
            "name": "Support Constant Math",
            "scope": "support.constant.math",
            "settings": {
                "foreground": "#F3F359"
            }
        },
        {
            "name": "Number",
            "scope": [
                "constant.numeric",
                "constant.character.numeric"
            ],
            "settings": {
                "foreground": "#f09030"
            }
        },
        {
            "name": "Built-in constant",
            "scope": [
                "constant.language",
                "punctuation.definition.constant",
                "variable.other.constant"
            ],
            "settings": {
                "foreground": "#f887ff"
            }
        },
        {
            "name": "User-defined constant",
            "scope": [
                "constant.character",
                "constant.other"
            ],
            "settings": {
                "foreground": "#f887ff"
            }
        },
        {
            "name": "Constant Character Escape",
            "scope": "constant.character.escape",
            "settings": {
                "foreground": "#f09030"
            }
        },
        {
            "name": "RegExp String",
            "scope": [
                "string.regexp",
                "string.regexp keyword.other"
            ],
            "settings": {
                "foreground": "#f887ff"
            }
        },
        {
            "name": "Comma in functions",
            "scope": "meta.function punctuation.separator.comma",
            "settings": {
                "foreground": "#eeeeee"
            }
        },
        {
            "name": "Variable",
            "scope": "variable",
            "settings": {
                "foreground": "#F3F359"
            }
        },
        {
            "name": "Keyword",
            "scope": [
                "punctuation.accessor",
                "keyword"
            ],
            "settings": {
                "foreground": "#eb0869"
            }
        },
        {
            "name": "Storage",
            "scope": "storage",
            "settings": {
                "foreground": "#eb0869"
            }
        },
        {
            "name": "Storage type",
            "scope": [
                "storage.type",
                "meta.var.expr storage.type",
                "meta.class meta.method.declaration meta.var.expr storage.type.js"
            ],
            "settings": {
                "foreground": "#eb0869"
            }
        },
        {
            "name": "Class name",
            "scope": [
                "entity.name.class",
                "meta.class entity.name.type.class"
            ],
            "settings": {
                "foreground": "#F3F359"
            }
        },
        {
            "name": "Inherited class",
            "scope": "entity.other.inherited-class",
            "settings": {
                "fontStyle": "italic",
                "foreground": "#06fbcf"
            }
        },
        {
            "name": "Function name",
            "scope": "entity.name.function",
            "settings": {
                "foreground": "#f887ff"
            }
        },
        {
            "name": "Function Parameters",
            "scope": "variable.parameter",
            "settings": {
                "foreground": "#B60DFC"
            }
        },
        {
            "name": "Meta Tag",
            "scope": [
                "punctuation.definition.tag",
                "meta.tag"
            ],
            "settings": {
                "foreground": "#f887ff"
            }
        },
        {
            "name": "HTML Tag names",
            "scope": [
                "entity.name.tag support.class.component",
                "meta.tag.other.html",
                "meta.tag.other.js",
                "meta.tag.other.tsx",
                "entity.name.tag.tsx",
                "entity.name.tag.js",
                "entity.name.tag",
                "meta.tag.js",
                "meta.tag.tsx",
                "meta.tag.html"
            ],
            "settings": {
                "foreground": "#eb0869"
            }
        },
        {
            "name": "Tag attribute",
            "scope": "entity.other.attribute-name",
            "settings": {
                "foreground": "#F3F359"
            }
        },
        {
            "name": "Entity Name Tag Custom",
            "scope": "entity.name.tag.custom",
            "settings": {
                "foreground": "#F3F359"
            }
        },
        {
            "name": "Library (function & constant)",
            "scope": [
                "support.function",
                "support.constant"
            ],
            "settings": {
                "foreground": "#f887ff"
            }
        },
        {
            "name": "Support Constant Property Value meta",
            "scope": "support.constant.meta.property-value",
            "settings": {
                "foreground": "#f887ff"
            }
        },
        {
            "name": "Library class/type",
            "scope": [
                "support.type",
                "support.class"
            ],
            "settings": {
                "foreground": "#F3F359"
            }
        },
        {
            "name": "Support Variable DOM",
            "scope": "support.variable.dom",
            "settings": {
                "foreground": "#F3F359"
            }
        },
        {
            "name": "Invalid",
            "scope": "invalid",
            "settings": {
                "foreground": "#eeeeee"
            }
        },
        {
            "name": "Invalid deprecated",
            "scope": "invalid.deprecated",
            "settings": {
                "foreground": "#eeeeee"
            }
        },
        {
            "name": "Keyword Operator",
            "scope": "keyword.operator",
            "settings": {
                "foreground": "#f887ff"
            }
        },
        {
            "name": "Keyword Operator Relational",
            "scope": "keyword.operator.relational",
            "settings": {
                "foreground": "#eb0869"
            }
        },
        {
            "name": "Keyword Operator Assignment",
            "scope": "keyword.operator.assignment",
            "settings": {
                "foreground": "#eb0869"
            }
        },
        {
            "name": "Double-Slashed Comment",
            "scope": "comment.line.double-slash",
            "settings": {
                "foreground": "#777777"
            }
        },
        {
            "name": "Object",
            "scope": "object",
            "settings": {
                "foreground": "#cccccc"
            }
        },
        {
            "name": "Null",
            "scope": "constant.language.null",
            "settings": {
                "foreground": "#eb0869"
            }
        },
        {
            "name": "Meta Brace",
            "scope": "meta.brace",
            "settings": {
                "foreground": "#eeeeee"
            }
        },
        {
            "name": "Meta Delimiter Period",
            "scope": "meta.delimiter.period",
            "settings": {
                "foreground": "#eb0869"
            }
        },
        {
            "name": "Punctuation Definition String",
            "scope": "punctuation.definition.string",
            "settings": {
                "foreground": "#32D698"
            }
        },
        {
            "name": "Boolean",
            "scope": "constant.language.boolean",
            "settings": {
                "foreground": "#eb0869"
            }
        },
        {
            "name": "Object Comma",
            "scope": "object.comma",
            "settings": {
                "foreground": "#eeeeee"
            }
        },
        {
            "name": "Variable Parameter Function",
            "scope": "variable.parameter.function",
            "settings": {
                "foreground": "#f887ff"
            }
        },
        {
            "name": "Support Type Property Name & entity name tags",
            "scope": [
                "support.type.vendored.property-name",
                "support.constant.vendored.property-value",
                "support.type.property-name",
                "meta.property-list entity.name.tag"
            ],
            "settings": {
                "foreground": "#f887ff"
            }
        },
        {
            "name": "Entity Name tag reference in stylesheets",
            "scope": "meta.property-list entity.name.tag.reference",
            "settings": {
                "foreground": "#eb0869"
            }
        },
        {
            "name": "Constant Other Color RGB Value Punctuation Definition Constant",
            "scope": "constant.other.color.rgb-value punctuation.definition.constant",
            "settings": {
                "foreground": "#f09030"
            }
        },
        {
            "name": "Constant Other Color",
            "scope": "constant.other.color",
            "settings": {
                "foreground": "#F3F359"
            }
        },
        {
            "name": "Keyword Other Unit",
            "scope": "keyword.other.unit",
            "settings": {
                "foreground": "#F3F359"
            }
        },
        {
            "name": "Meta Selector",
            "scope": "meta.selector",
            "settings": {
                "foreground": "#eb0869"
            }
        },
        {
            "name": "Entity Other Attribute Name Id",
            "scope": "entity.other.attribute-name.id",
            "settings": {
                "foreground": "#FAD430"
            }
        },
        {
            "name": "Meta Property Name",
            "scope": "meta.property-name",
            "settings": {
                "foreground": "#f887ff"
            }
        },
        {
            "name": "Doctypes",
            "scope": [
                "entity.name.tag.doctype",
                "meta.tag.sgml.doctype"
            ],
            "settings": {
                "foreground": "#eb0869"
            }
        },
        {
            "name": "Punctuation Definition Parameters",
            "scope": "punctuation.definition.parameters",
            "settings": {
                "foreground": "#32D698"
            }
        },
        {
            "name": "Keyword Control Operator",
            "scope": "keyword.control.operator",
            "settings": {
                "foreground": "#f887ff"
            }
        },
        {
            "name": "Keyword Operator Logical",
            "scope": "keyword.operator.logical",
            "settings": {
                "foreground": "#eb0869"
            }
        },
        {
            "name": "Variable Instances",
            "scope": [
                "variable.instance",
                "variable.other.instance",
                "variable.reaedwrite.instance",
                "variable.other.readwrite.instance"
            ],
            "settings": {
                "foreground": "#eb0869"
            }
        },
        {
            "name": "Variable Property Other",
            "scope": [
                "variable.other.property",
                "variable.other.object.property"
            ],
            "settings": {
                "foreground": "#f887ff"
            }
        },
        {
            "name": "Entity Name Function",
            "scope": "entity.name.function",
            "settings": {
                "foreground": "#f887ff"
            }
        },
        {
            "name": "Keyword Operator Comparison",
            "scope": "keyword.operator.comparison",
            "settings": {
                "foreground": "#eb0869"
            }
        },
        {
            "name": "Support Constant, `new` keyword, Special Method Keyword",
            "scope": [
                "support.constant",
                "keyword.other.special-method",
                "keyword.other.new"
            ],
            "settings": {
                "foreground": "#f887ff"
            }
        },
        {
            "name": "Support Function",
            "scope": "support.function",
            "settings": {
                "foreground": "#f887ff"
            }
        },
        {
            "name": "Invalid Broken",
            "scope": "invalid.broken",
            "settings": {
                "foreground": "#020e14"
            }
        },
        {
            "name": "Invalid Unimplemented",
            "scope": "invalid.unimplemented",
            "settings": {
                "foreground": "#eeeeee"
            }
        },
        {
            "name": "Invalid Illegal",
            "scope": "invalid.illegal",
            "settings": {
                "foreground": "#eeeeee"
            }
        },
        {
            "name": "Language Variable",
            "scope": "variable.language",
            "settings": {
                "foreground": "#eb0869"
            }
        },
        {
            "name": "Support Variable Property",
            "scope": "support.variable.property",
            "settings": {
                "foreground": "#f887ff"
            }
        },
        {
            "name": "Variable Function",
            "scope": "variable.function",
            "settings": {
                "foreground": "#f887ff"
            }
        },
        {
            "name": "Variable Interpolation",
            "scope": "variable.interpolation",
            "settings": {
                "foreground": "#ec5f67"
            }
        },
        {
            "name": "Meta Function Call",
            "scope": "meta.function-call",
            "settings": {
                "foreground": "#f887ff"
            }
        },
        {
            "name": "Punctuation Section Embedded",
            "scope": "punctuation.section.embedded",
            "settings": {
                "foreground": "#d3423e"
            }
        },
        {
            "name": "Punctuation Tweaks",
            "scope": [
                "punctuation.terminator.expression",
                "punctuation.definition.arguments",
                "punctuation.definition.array",
                "punctuation.section.array",
                "meta.array"
            ],
            "settings": {
                "foreground": "#eeeeee"
            }
        },
        {
            "scope": "punctuation.terminator",
            "settings": {
                "foreground": "#eb0869"
            }
        },
        {
            "name": "More Punctuation Tweaks",
            "scope": [
                "punctuation.definition.list.begin",
                "punctuation.definition.list.end",
                "punctuation.separator.arguments",
                "punctuation.definition.list"
            ],
            "settings": {
                "foreground": "#32D698"
            }
        },
        {
            "name": "Template Strings",
            "scope": "string.template meta.template.expression",
            "settings": {
                "foreground": "#d3423e"
            }
        },
        {
            "name": "Backtics(``) in Template Strings",
            "scope": "string.template punctuation.definition.string",
            "settings": {
                "foreground": "#ffffff"
            }
        },
        {
            "name": "Italics",
            "scope": "italic",
            "settings": {
                "foreground": "#eb0869",
                "fontStyle": "italic"
            }
        },
        {
            "name": "Bold",
            "scope": "bold",
            "settings": {
                "foreground": "#F3F359",
                "fontStyle": "bold"
            }
        },
        {
            "name": "Quote",
            "scope": "quote",
            "settings": {
                "foreground": "#777777",
                "fontStyle": "italic"
            }
        },
        {
            "name": "Raw Code",
            "scope": "raw",
            "settings": {
                "foreground": "#f887ff"
            }
        },
        {
            "name": "CoffeScript Variable Assignment",
            "scope": "variable.assignment.coffee",
            "settings": {
                "foreground": "#f887ff"
            }
        },
        {
            "name": "CoffeScript Parameter Function",
            "scope": "variable.parameter.function.coffee",
            "settings": {
                "foreground": "#eeeeee"
            }
        },
        {
            "name": "CoffeeScript Assignments",
            "scope": "variable.assignment.coffee",
            "settings": {
                "foreground": "#f887ff"
            }
        },
        {
            "name": "C# Readwrite Variables",
            "scope": "variable.other.readwrite.cs",
            "settings": {
                "foreground": "#eeeeee"
            }
        },
        {
            "name": "C# Classes & Storage types",
            "scope": [
                "entity.name.type.class.cs",
                "storage.type.cs"
            ],
            "settings": {
                "foreground": "#87E1FF"
            }
        },
        {
            "name": "C# Namespaces",
            "scope": "entity.name.type.namespace.cs",
            "settings": {
                "foreground": "#cccccc"
            }
        },
        {
            "name": "Tag names in Stylesheets",
            "scope": [
                "entity.name.tag.css",
                "entity.name.tag.less",
                "entity.name.tag.custom.css"
            ],
            "settings": {
                "foreground": "#eb0869"
            }
        },
        {
            "name": "Wildcard(*) selector in Stylesheets",
            "scope": [
                "entity.name.tag.wildcard.css",
                "entity.name.tag.wildcard.less",
                "entity.name.tag.wildcard.scss",
                "entity.name.tag.wildcard.sass"
            ],
            "settings": {
                "foreground": "#eb0869"
            }
        },
        {
            "name": "CSS Keyword Other Unit",
            "scope": "keyword.other",
            "settings": {
                "foreground": "#F3F359"
            }
        },
        {
            "name": "Attribute Name for CSS",
            "scope": "meta.attribute-selector.css entity.other.attribute-name.attribute",
            "settings": {
                "foreground": "#f09030"
            }
        },
        {
            "name": "Elixir Classes",
            "scope": [
                "source.elixir support.type.elixir",
                "source.elixir meta.module.elixir entity.name.class.elixir"
            ],
            "settings": {
                "foreground": "#f887ff"
            }
        },
        {
            "name": "Elixir Functions",
            "scope": "source.elixir entity.name.function",
            "settings": {
                "foreground": "#F3F359"
            }
        },
        {
            "name": "Elixir Constants",
            "scope": [
                "source.elixir constant.other.symbol.elixir",
                "source.elixir constant.other.keywords.elixir"
            ],
            "settings": {
                "foreground": "#f887ff"
            }
        },
        {
            "name": "Elixir String Punctuations",
            "scope": "source.elixir punctuation.definition.string",
            "settings": {
                "foreground": "#f887ff"
            }
        },
        {
            "name": "Elixir",
            "scope": [
                "source.elixir variable.other.readwrite.module.elixir",
                "source.elixir variable.other.readwrite.module.elixir punctuation.definition.variable.elixir"
            ],
            "settings": {
                "foreground": "#F3F359"
            }
        },
        {
            "name": "Elixir Binary Punctuations",
            "scope": "source.elixir .punctuation.binary.elixir",
            "settings": {
                "foreground": "#eb0869"
            }
        },
        {
            "name": "Go Function Calls",
            "scope": "source.go meta.function-call.go",
            "settings": {
                "foreground": "#eeeeee"
            }
        },
        {
            "name": "ID Attribute Name in HTML",
            "scope": "entity.other.attribute-name.id.html",
            "settings": {
                "foreground": "#F3F359"
            }
        },
        {
            "name": "HTML Punctuation Definition Tag",
            "scope": "punctuation.definition.tag.html",
            "settings": {
                "foreground": "#f887ff"
            }
        },
        {
            "name": "HTML Doctype",
            "scope": "meta.tag.sgml.doctype.html",
            "settings": {
                "foreground": "#eb0869"
            }
        },
        {
            "name": "JavaScript Classes",
            "scope": "meta.class entity.name.type.class.js",
            "settings": {
                "foreground": "#f09030"
            }
        },
        {
            "name": "JavaScript Method Declaration e.g. `constructor`",
            "scope": "meta.method.declaration storage.type.js",
            "settings": {
                "foreground": "#f887ff",
                "fontStyle": ""
            }
        },
        {
            "name": "JavaScript Terminator",
            "scope": "terminator.js",
            "settings": {
                "foreground": "#eeeeee"
            }
        },
        {
            "name": "JavaScript Meta Punctuation Definition",
            "scope": "meta.js punctuation.definition.js",
            "settings": {
                "foreground": "#eeeeee"
            }
        },
        {
            "name": "Entity Names in Code Documentations",
            "scope": [
                "entity.name.type.instance.jsdoc",
                "entity.name.type.instance.phpdoc"
            ],
            "settings": {
                "foreground": "#eeeeee"
            }
        },
        {
            "name": "Other Variables in Code Documentations",
            "scope": [
                "variable.other.jsdoc",
                "variable.other.phpdoc"
            ],
            "settings": {
                "foreground": "#78ccf0"
            }
        },
        {
            "name": "JavaScript module imports and exports",
            "scope": [
                "variable.other.meta.import.js",
                "meta.import.js variable.other",
                "variable.other.meta.export.js",
                "meta.export.js variable.other"
            ],
            "settings": {
                "foreground": "#eeeeee"
            }
        },
        {
            "name": "JavaScript Variable Parameter Function",
            "scope": "variable.parameter.function.js",
            "settings": {
                "foreground": "#B60DFC"
            }
        },
        {
            "name": "JavaScript Variable Other ReadWrite",
            "scope": "variable.other.readwrite.js",
            "settings": {
                "foreground": "#ffffff"
            }
        },
        {
            "name": "JavaScript[React] Variable Other Object",
            "scope": [
                "variable.other.object.js",
                "variable.other.object.jsx",
                "variable.object.property.js",
                "variable.object.property.jsx"
            ],
            "settings": {
                "foreground": "#ffffff"
            }
        },
        {
            "name": "JavaScript Variables",
            "scope": [
                "variable.js",
                "variable.other.js"
            ],
            "settings": {
                "foreground": "#ffffff"
            }
        },
        {
            "name": "JavaScript Entity Name Type",
            "scope": [
                "entity.name.type.js",
                "entity.name.type.module.js"
            ],
            "settings": {
                "foreground": "#f09030"
            }
        },
        {
            "name": "JavaScript Support Classes",
            "scope": "support.class.js",
            "settings": {
                "foreground": "#ffffff"
            }
        },
        {
            "name": "JSON Property Names",
            "scope": "support.type.property-name.json",
            "settings": {
                "foreground": "#32D698"
            }
        },
        {
            "name": "JSON Support Constants",
            "scope": "support.constant.json",
            "settings": {
                "foreground": "#F3F359"
            }
        },
        {
            "name": "JSON Property values (string)",
            "scope": "meta.structure.dictionary.value.json string.quoted.double",
            "settings": {
                "foreground": "#f887ff"
            }
        },
        {
            "name": "Strings in JSON values",
            "scope": "string.quoted.double.json punctuation.definition.string.json",
            "settings": {
                "foreground": "#f887ff"
            }
        },
        {
            "name": "Specific JSON Property values like null",
            "scope": "meta.structure.dictionary.json meta.structure.dictionary.value constant.language",
            "settings": {
                "foreground": "#eb0869"
            }
        },
        {
            "name": "Ruby Variables",
            "scope": "variable.other.ruby",
            "settings": {
                "foreground": "#ffffff"
            }
        },
        {
            "name": "Ruby Hashkeys",
            "scope": "constant.language.symbol.hashkey.ruby",
            "settings": {
                "foreground": "#f887ff"
            }
        },
        {
            "name": "LESS Tag names",
            "scope": "entity.name.tag.less",
            "settings": {
                "foreground": "#eb0869"
            }
        },
        {
            "name": "LESS Keyword Other Unit",
            "scope": "keyword.other.unit.css",
            "settings": {
                "foreground": "#F3F359"
            }
        },
        {
            "name": "Attribute Name for LESS",
            "scope": "meta.attribute-selector.less entity.other.attribute-name.attribute",
            "settings": {
                "foreground": "#f09030"
            }
        },
        {
            "name": "Markdown Headings",
            "scope": "markup.heading.markdown",
            "settings": {
                "foreground": "#f887ff"
            }
        },
        {
            "name": "Markdown Italics",
            "scope": "markup.italic.markdown",
            "settings": {
                "foreground": "#eb0869",
                "fontStyle": "italic"
            }
        },
        {
            "name": "Markdown Bold",
            "scope": "markup.bold.markdown",
            "settings": {
                "foreground": "#F3F359",
                "fontStyle": "bold"
            }
        },
        {
            "name": "Markdown Quote + others",
            "scope": "markup.quote.markdown",
            "settings": {
                "foreground": "#777777",
                "fontStyle": "italic"
            }
        },
        {
            "name": "Markdown Raw Code + others",
            "scope": "markup.inline.raw.markdown",
            "settings": {
                "foreground": "#f887ff"
            }
        },
        {
            "name": "Markdown Links",
            "scope": [
                "markup.underline.link.markdown",
                "markup.underline.link.image.markdown"
            ],
            "settings": {
                "foreground": "#eb0869"
            }
        },
        {
            "name": "Markdown Link Title and Description",
            "scope": [
                "string.other.link.title.markdown",
                "string.other.link.description.markdown"
            ],
            "settings": {
                "foreground": "#ffffff"
            }
        },
        {
            "name": "Markdown Punctuation",
            "scope": [
                "punctuation.definition.string.markdown",
                "punctuation.definition.string.begin.markdown",
                "punctuation.definition.string.end.markdown",
                "meta.link.inline.markdown punctuation.definition.string"
            ],
            "settings": {
                "foreground": "#f887ff"
            }
        },
        {
            "name": "Markdown MetaData Punctuation",
            "scope": [
                "punctuation.definition.metadata.markdown"
            ],
            "settings": {
                "foreground": "#eb0869"
            }
        },
        {
            "name": "Markdown List Punctuation",
            "scope": [
                "beginning.punctuation.definition.list.markdown"
            ],
            "settings": {
                "foreground": "#f887ff"
            }
        },
        {
            "name": "PHP Variables",
            "scope": "variable.other.php",
            "settings": {
                "foreground": "#ffffff"
            }
        },
        {
            "name": "Support Classes in PHP",
            "scope": "support.class.php",
            "settings": {
                "foreground": "#f09030"
            }
        },
        {
            "name": "Punctuations in PHP function calls",
            "scope": "meta.function-call.php punctuation",
            "settings": {
                "foreground": "#ffffff"
            }
        },
        {
            "name": "PHP Global Variables",
            "scope": "variable.other.global.php",
            "settings": {
                "foreground": "#F3F359"
            }
        },
        {
            "name": "Declaration Punctuation in PHP Global Variables",
            "scope": "variable.other.global.php punctuation.definition.variable",
            "settings": {
                "foreground": "#F3F359"
            }
        },
        {
            "name": "Language Constants in Python",
            "scope": "constant.language.python",
            "settings": {
                "foreground": "#eb0869"
            }
        },
        {
            "name": "Python Function Parameter and Arguments",
            "scope": [
                "variable.parameter.function.python",
                "meta.function-call.arguments.python"
            ],
            "settings": {
                "foreground": "#B60DFC"
            }
        },
        {
            "name": "Python Function Call",
            "scope": [
                "meta.function-call.python",
                "meta.function-call.generic.python"
            ],
            "settings": {
                "foreground": "#cccccc"
            }
        },
        {
            "name": "Punctuations in Python",
            "scope": "punctuation.python",
            "settings": {
                "foreground": "#ffffff"
            }
        },
        {
            "name": "Decorator Functions in Python",
            "scope": "entity.name.function.decorator.python",
            "settings": {
                "foreground": "#F3F359"
            }
        },
        {
            "name": "Python Language Variable",
            "scope": "source.python variable.language.special",
            "settings": {
                "foreground": "#f887ff"
            }
        },
        {
            "name": "SCSS Variable",
            "scope": [
                "variable.scss",
                "variable.sass",
                "variable.parameter.url.scss",
                "variable.parameter.url.sass"
            ],
            "settings": {
                "foreground": "#ffffff"
            }
        },
        {
            "name": "Variables in SASS At-Rules",
            "scope": [
                "source.css.scss meta.at-rule variable",
                "source.css.sass meta.at-rule variable"
            ],
            "settings": {
                "foreground": "#f887ff"
            }
        },
        {
            "name": "Variables in SASS At-Rules",
            "scope": [
                "source.css.scss meta.at-rule variable",
                "source.css.sass meta.at-rule variable"
            ],
            "settings": {
                "foreground": "#ffffff"
            }
        },
        {
            "name": "Attribute Name for SASS",
            "scope": [
                "meta.attribute-selector.scss entity.other.attribute-name.attribute",
                "meta.attribute-selector.sass entity.other.attribute-name.attribute"
            ],
            "settings": {
                "foreground": "#f09030"
            }
        },
        {
            "name": "Tag names in SASS",
            "scope": [
                "entity.name.tag.scss",
                "entity.name.tag.sass"
            ],
            "settings": {
                "foreground": "#eb0869"
            }
        },
        {
            "name": "SASS Keyword Other Unit",
            "scope": [
                "keyword.other.unit.scss",
                "keyword.other.unit.sass"
            ],
            "settings": {
                "foreground": "#F3F359"
            }
        },
        {
            "name": "TypeScript[React] Variables and Object Properties",
            "scope": [
                "variable.other.readwrite.alias.ts",
                "variable.other.readwrite.alias.tsx",
                "variable.other.readwrite.ts",
                "variable.other.readwrite.tsx",
                "variable.other.object.ts",
                "variable.other.object.tsx",
                "variable.object.property.ts",
                "variable.object.property.tsx",
                "variable.other.ts",
                "variable.other.tsx",
                "variable.tsx",
                "variable.ts"
            ],
            "settings": {
                "foreground": "#ffffff"
            }
        },
        {
            "name": "TypeScript[React] Entity Name Types",
            "scope": [
                "entity.name.type.ts",
                "entity.name.type.tsx"
            ],
            "settings": {
                "foreground": "#78ccf0"
            }
        },
        {
            "name": "TypeScript[React] Node Classes",
            "scope": [
                "support.class.node.ts",
                "support.class.node.tsx"
            ],
            "settings": {
                "foreground": "#f887ff"
            }
        },
        {
            "name": "TypeScript[React] Entity Name Types as Parameters",
            "scope": [
                "meta.type.parameters.ts entity.name.type",
                "meta.type.parameters.tsx entity.name.type"
            ],
            "settings": {
                "foreground": "#ffffff"
            }
        },
        {
            "name": "TypeScript[React] Import/Export Punctuations",
            "scope": [
                "meta.import.ts punctuation.definition.block",
                "meta.import.tsx punctuation.definition.block",
                "meta.export.ts punctuation.definition.block",
                "meta.export.tsx punctuation.definition.block"
            ],
            "settings": {
                "foreground": "#ffffff"
            }
        },
        {
            "name": "TypeScript[React] Punctuation Decorators",
            "scope": [
                "meta.decorator punctuation.decorator.ts",
                "meta.decorator punctuation.decorator.tsx"
            ],
            "settings": {
                "foreground": "#f887ff"
            }
        },
        {
            "name": "TypeScript[React] Punctuation Decorators",
            "scope": [
                "meta.jsx.children.tsx",
                "meta.tag.js meta.jsx.children.tsx"
            ],
            "settings": {
                "foreground": "#f887ff"
            }
        },
        {
            "name": "YAML Entity Name Tags",
            "scope": "entity.name.tag.yaml",
            "settings": {
                "foreground": "#f887ff"
            }
        },
        {
            "name": "Normalize font style of certain Components",
            "scope": [
                "meta.property-list.css meta.property-value.css variable.other.less",
                "meta.property-list.scss variable.scss",
                "meta.property-list.sass variable.sass",
                "keyword.operator.logical",
                "keyword.operator.arithmetic",
                "keyword.operator.bitwise",
                "keyword.operator.increment",
                "keyword.operator.ternary",
                "keyword.operator.comparison",
                "keyword.operator.assignment",
                "keyword.operator.operator",
                "keyword.operator.or.regexp",
                "punctuation.definintion.string",
                "punctuation"
            ],
            "settings": {
                "fontStyle": ""
            }
        }
    ]
}